ggspy/__init__.py
ggspy/__version__.py
ggspy/ggs.py
ggspy-1.0.0.dist-info/METADATA
ggspy-1.0.0.dist-info/WHEEL
ggspy-1.0.0.dist-info/top_level.txt
ggspy-1.0.0.dist-info/RECORD
