Metadata-Version: 2.1
Name: ggspy
Version: 1.0.0
Summary: Implementation of Greedy Gaussian Segmentation based on HALLAC 2018
Home-page: https://github.com/labrunhosarodrigues/greedy-gaussian-segmentation
Author: Lourenço A. rodrigues
Author-email: labrunhosarodrigues@gmail.com
Classifier: Programming Language :: Python
Classifier: Programming Language :: Python :: 3
Classifier: Programming Language :: Python :: 3.6
Classifier: Programming Language :: Python :: 3.7
Classifier: Programming Language :: Python :: 3.8
Classifier: Programming Language :: Python :: Implementation :: CPython
Requires-Python: >=3.7.3
Requires-Dist: numpy
Provides-Extra: dev
Requires-Dist: plotly ; extra == 'dev'
